alens/importers/__init__.py
alens/importers/dedup.py
alens/importers/drnuke-ibkr.py
alens/importers/ibflex.py
alens/importers/tarioch-ibkr.py
alens/importers/uabean-ibkr.py
alens/importers/utilities.py
alens/importers/vanguard_au.py
alens_importers-0.10.1.dist-info/METADATA
alens_importers-0.10.1.dist-info/WHEEL
alens_importers-0.10.1.dist-info/licenses/LICENSE
alens_importers-0.10.1.dist-info/RECORD
