Metadata-Version: 2.4
Name: alens-importers
Version: 0.10.1
Summary: Importers for Beancount's beangulp
Project-URL: repository, https://github.com/alensiljak/alens-importers
License-File: LICENSE
Requires-Python: >=3.12
Requires-Dist: beancount>=3.1.0
Requires-Dist: beangulp>=0.2.0
Requires-Dist: ibflex
Requires-Dist: loguru>=0.7.3
Requires-Dist: requests>=2.32.3
